[
  {
    "title": "Civic Auditorium construction, 1928",
    "identifier": "spl_shp_14124",
    "description": "Transcribed from photograph: \"Buildings. Civic auditorium. Under construction, 1928. Schack, Young and Myers, architects.\"",
    "subjects": [
      "Buildings--Washington (State)--Seattle",
      "Civic Auditorium (Seattle, Wash.)",
      "Auditoriums--Washington (State)--Seattle",
      "Construction--Washington (State)--Seattle"
    ],
    "photographer": "",
    "intersection": "",
    "coordinates": [
      47.623948,
      -122.350088
    ],
    "createdDate": "1928-01-01T00:00:00.000Z",
    "image": "https://cdm16118.contentdm.oclc.org/digital/api/singleitem/image/p15015coll4/1692/default.jpg"
  },
  {
    "title": "Battleship Nebraska, ca. 1904",
    "identifier": "spl_shp_14231",
    "description": "Transcribed from photograph: \"Ships. Nebraska (Battleship). Built in Seattle at the Moran Brothers Shipyards. Launched Oct. 7, 1904; scrapped 1923.\"",
    "subjects": [
      "Moran, Robert, 1857-1943",
      "Moran Brothers Company (Seattle, Wash.)",
      "Shipyards--Washington (State)--Seattle",
      "Shipbuilding--Washington (State)--Seattle",
      "Nebraska (Battleship)",
      "Battleships"
    ],
    "photographer": "",
    "intersection": "",
    "coordinates": [
      47.607427,
      -122.370833
    ],
    "createdDate": "1904-01-01T08:00:00.000Z",
    "image": "https://cdm16118.contentdm.oclc.org/digital/api/singleitem/image/p15015coll4/1707/default.jpg"
  },
  {
    "title": "Fremont Avenue, 1898",
    "identifier": "spl_shp_14272",
    "description": "Transcribed from photograph: \"Streets. Fremont Ave., 47th-48th. 1898.\"",
    "subjects": [
      "Buildings--Washington (State)--Seattle",
      "Dwellings--Washington (State)--Seattle",
      "Fremont Avenue North (Seattle, Wash.)",
      "North Forty-seventh Street (Seattle, Wash.)",
      "North Forty-eighth Street (Seattle, Wash.)",
      "Dairy cattle"
    ],
    "photographer": "Conn, Margaret, 1864-1942",
    "intersection": "N. 47th St. and Fremont Ave.",
    "coordinates": [
      47.662882,
      -122.350019
    ],
    "createdDate": "1898-01-01T00:00:00.000Z",
    "image": "https://cdm16118.contentdm.oclc.org/digital/api/singleitem/image/p15015coll4/1714/default.jpg"
  },
  {
    "title": "Alaska Yukon Pacific Exposition at Night, 1909",
    "identifier": "spl_shp_14163",
    "description": "Transcribed from photograph: \"Alaska Yukon Pacific Exposition. 1909. General view at night from Lake Union. Howard & Galloway, supervising architects. J.R. Thompson, designer of lighting effects.\"",
    "subjects": [
      "Alaska-Yukon-Pacific Exposition (1909 : Seattle, Wash.)",
      "Exhibition buildings--Washington (State)--Seattle",
      "Union, Lake (Wash.)",
      "Thompson, J.R.",
      "Exterior lighting"
    ],
    "photographer": "",
    "intersection": "",
    "coordinates": [
      47.65237,
      -122.308966
    ],
    "createdDate": "1909-01-01T00:00:00.000Z",
    "image": "https://cdm16118.contentdm.oclc.org/digital/api/singleitem/image/p15015coll4/1705/default.jpg"
  },
  {
    "title": "John Noble Wallingford, ca. 1893",
    "identifier": "spl_shp_14275",
    "description": "Transcribed from photograph: \"Portraits. Wallingford, John Noble. 1833-1930 or 1931.\"",
    "subjects": [
      "Wallingford (Seattle, Wash.)",
      "Wallingford, John Noble, 1834-1913--Portraits",
      "Portraits--Washington (State)--Seattle"
    ],
    "photographer": "",
    "intersection": "",
    "coordinates": [
      null
    ],
    "createdDate": "1893-01-01T08:00:00.000Z",
    "image": "https://cdm16118.contentdm.oclc.org/digital/api/singleitem/image/p15015coll4/1715/default.jpg"
  },
  {
    "title": "Budlong House, ca. 1898",
    "identifier": "spl_shp_14270",
    "description": "Transcribed from photograph: \"Houses. Budlong House at Aurora Ave. and Ewing St. [N. 34th St.] About 1898.\"",
    "subjects": [
      "Budlong family",
      "Buildings--Washington (State)--Seattle",
      "Dwellings--Washington (State)--Seattle",
      "Aurora Avenue (Seattle and Shoreline, Wash.)",
      "North Thirty-fourth Street (Seattle, Wash.)"
    ],
    "photographer": "Conn, Margaret, 1864-1942",
    "intersection": "N. 34th St. and Aurora Ave. N.",
    "coordinates": [
      47.649225,
      -122.347402
    ],
    "createdDate": "1898-01-01T08:00:00.000Z",
    "image": "https://cdm16118.contentdm.oclc.org/digital/api/singleitem/image/p15015coll4/1713/default.jpg"
  },
  {
    "title": "Construction of Denny Hall, 1895",
    "identifier": "spl_shp_14235",
    "description": "Transcribed from photograph: \"Colleges & Universities. Washington (State) University. Denny hall. Exterior, under construction. 1895. Photo by C.L. Andrews (copyrighted 1909). Charles Saunders, architect.\"",
    "subjects": [
      "University of Washington",
      "Buildings--Washington (State)--Seattle",
      "Construction--Washington (State)--Seattle",
      "Denny Hall (Seattle, Wash.)",
      "Scaffolding"
    ],
    "photographer": "Andrews, Clarence Leroy, 1862-1948",
    "intersection": "",
    "coordinates": [
      47.658393,
      -122.308833
    ],
    "createdDate": "1895-01-01T00:00:00.000Z",
    "image": "https://cdm16118.contentdm.oclc.org/digital/api/singleitem/image/p15015coll4/1711/default.jpg"
  },
  {
    "title": "Yesler Mansion, ca. 1900",
    "identifier": "spl_shp_14220",
    "description": "Transcribed from photograph: \"Public Library. 1899-1901. Building. Third Avenue and James Street. Built 1883 by Henry L. Yesler as a residence. Destroyed by fire 1901.\"",
    "subjects": [
      "Seattle Public Library",
      "Library buildings--Washington (State)--Seattle",
      "Seattle Central Library",
      "Third Avenue (Seattle, Wash.)",
      "James Street (Seattle, Wash.)",
      "Yesler, Henry L. (Henry Leiter), 1810-1892",
      "Buildings--Washington (State)--Seattle",
      "Dwellings--Washington (State)--Seattle"
    ],
    "photographer": "Wilse, Anders Beer, 1865-1949",
    "intersection": "3rd Ave. and James St.",
    "coordinates": [
      47.602768,
      -122.331409
    ],
    "createdDate": "1900-01-01T08:00:00.000Z",
    "image": "https://cdm16118.contentdm.oclc.org/digital/api/singleitem/image/p15015coll4/1706/default.jpg"
  },
  {
    "title": "View west from 7th Ave. and Jefferson St., 1900",
    "identifier": "spl_shp_14233",
    "description": "Transcribed from photograph: \"Views. From Seventh Ave. and Jefferson St. 1900. Looking West. Taken from the King County Courthouse.\"",
    "subjects": [
      "Elliott Bay (Wash.)",
      "Waterfronts--Washington (State)--Seattle",
      "Central business districts--Washington (State)--Seattle",
      "Seventh Avenue (Seattle, Wash.)",
      "Jefferson Street (Seattle, Wash.)",
      "Buildings--Washington (State)--Seattle",
      "Courthouses--Washington (State)--Seattle",
      "Courthouses--Washington (State)--King County",
      "King County Courthouse (Seattle, Wash.)",
      "Courts--Washington (State)--Seattle",
      "Courts--Washington (State)--King County"
    ],
    "photographer": "Conn, Margaret, 1864-1942",
    "intersection": "7th Ave. and Jefferson St.",
    "coordinates": [
      47.603921,
      -122.326443
    ],
    "createdDate": "1900-01-01T00:00:00.000Z",
    "image": "https://cdm16118.contentdm.oclc.org/digital/api/singleitem/image/p15015coll4/1709/default.jpg"
  },
  {
    "title": "View west from 7th Ave. and Jefferson St., 1900",
    "identifier": "spl_shp_14232",
    "description": "Transcribed from photograph: \"Views. From Seventh Ave. and Jefferson St. 1900. Looking Northwest. Taken from the King County Courthouse.\"",
    "subjects": [
      "Elliott Bay (Wash.)",
      "West Seattle (Seattle, Wash.)",
      "Waterfronts--Washington (State)--Seattle",
      "Central business districts--Washington (State)--Seattle",
      "Flags--United States",
      "Seventh Avenue (Seattle, Wash.)",
      "Jefferson Street (Seattle, Wash.)",
      "Buildings--Washington (State)--Seattle",
      "Courthouses--Washington (State)--Seattle",
      "Courthouses--Washington (State)--King County",
      "King County Courthouse (Seattle, Wash.)",
      "Courts--Washington (State)--Seattle",
      "Courts--Washington (State)--King County"
    ],
    "photographer": "",
    "intersection": "7th Ave. and Jefferson St.",
    "coordinates": [
      47.603921,
      -122.326443
    ],
    "createdDate": "1900-01-01T00:00:00.000Z",
    "image": "https://cdm16118.contentdm.oclc.org/digital/api/singleitem/image/p15015coll4/1708/default.jpg"
  },
  {
    "title": "Engine Company No. 1, ca. 1879",
    "identifier": "spl_shp_14268",
    "description": "Transcribed from photograph: \"Portraits. Group. Engine Co. No. 1: Hose team. About 1879. 1. Ira Hummel 2. Frank Beattie 3. Charles Maidment 4. Sherman Moran 5. James Quilter 6. James McIntyre 7. Bert Grow 8. Alex Meister 9. Anthony LeBrash 10. Will Perry 11. Miles Wiggin 12. Angie Kollock 13. James Roper.\" Transcribed from back of photo: \"Hose Team of Engine Co. No 1, Seattle Wash. Lev. McClure & Qui.\" \"Wm L. Lindsley. 222 West Lee St.\"",
    "subjects": [
      "Portraits, Group--Washington (State)--Seattle",
      "Volunteer fire fighters",
      "Volunteer fire departments--Washington (State)--Seattle",
      "Fire Engine Company No. 1 (Seattle, Wash.)",
      "Hummel, Ira, 1864-",
      "Beattie, Frank R., 1865-1954",
      "Maidment, Charles, 1866-",
      "Moran, Sherman, 1865-1929",
      "Quilter, James M., 1858-1925",
      "McIntyre, James",
      "Grow, Bert",
      "Meister, Alex",
      "LeBrash, Anthony",
      "Perry, William A.",
      "Wiggin, Miles R.",
      "Kollock, Archie M.",
      "Roper, James"
    ],
    "photographer": "",
    "intersection": "",
    "coordinates": [
      null
    ],
    "createdDate": "1879-01-01T00:00:00.000Z",
    "image": "https://cdm16118.contentdm.oclc.org/digital/api/singleitem/image/p15015coll4/1712/default.jpg"
  },
  {
    "title": "Elephant on parade at Pine St. and 3rd Ave., 1899",
    "identifier": "spl_shp_14234",
    "description": "Transcribed from photograph: \"Parades. Pine St. and Third Ave. 1899.\"",
    "subjects": [
      "Parades--Washington (State)--Seattle",
      "Central business districts--Washington (State)--Seattle",
      "Pine Street (Seattle, Wash.)",
      "Third Avenue (Seattle, Wash.)",
      "Elephants",
      "Crowds"
    ],
    "photographer": "Conn, Margaret, 1864-1942",
    "intersection": "3rd Ave. and Pine St.",
    "coordinates": [
      47.610823,
      -122.338668
    ],
    "createdDate": "1899-01-01T00:00:00.000Z",
    "image": "https://cdm16118.contentdm.oclc.org/digital/api/singleitem/image/p15015coll4/1710/default.jpg"
  },
  {
    "title": "John W. Denny House, 1906",
    "identifier": "spl_shp_14162",
    "description": "Transcribed from photograph: \"Houses. Denny, John W. House at North 92nd St. and Corliss Ave. 1906. Lora Denny making soap.\"",
    "subjects": [
      "Buildings--Washington (State)--Seattle",
      "Dwellings--Washington (State)--Seattle",
      "Soap",
      "North Ninety-second Street (Seattle, Wash.)",
      "Corliss Avenue North (Seattle, Wash.)",
      "Denny, John W. (John William), 1844-1923",
      "Denny, Lora Maud, 1883-1982"
    ],
    "photographer": "",
    "intersection": "Corliss Ave. N. and N. 92nd St.",
    "coordinates": [
      47.695927,
      -122.331117
    ],
    "createdDate": "1906-01-01T00:00:00.000Z",
    "image": "https://cdm16118.contentdm.oclc.org/digital/api/singleitem/image/p15015coll4/1704/default.jpg"
  },
  {
    "title": "Yesler's Mill, 1893",
    "identifier": "spl_shp_14291",
    "description": "Transcribed from photograph: \"Yesler (town). Yesler's mill. Built 1890. 1893. Now Laurelhurst.\"",
    "subjects": [
      "Laurelhurst (Seattle, Wash.)",
      "Yesler, Henry L. (Henry Leiter), 1810-1892",
      "Sawmills--Washington (State)--Seattle",
      "Docks--Washington (State)--Seattle",
      "Piers--Washington (State)--Seattle",
      "Wharves--Washington (State)--Seattle",
      "Docks--Washington (State)--Seattle",
      "Washington, Lake (Wash.)"
    ],
    "photographer": "Conn, Margaret, 1864-1942",
    "intersection": "",
    "coordinates": [
      47.65,
      -122.276988
    ],
    "createdDate": "1893-01-01T00:00:00.000Z",
    "image": "https://cdm16118.contentdm.oclc.org/digital/api/singleitem/image/p15015coll4/1725/default.jpg"
  },
  {
    "title": "Yesler (Town), 1893",
    "identifier": "spl_shp_14288",
    "description": "Transcribed from photograph: \"Yesler (town). View of town. Looking Southwest. 1893. Now Laurelhurst.\"",
    "subjects": [
      "Laurelhurst (Seattle, Wash.)",
      "Buildings--Washington (State)--Seattle",
      "Dwellings--Washington (State)--Seattle",
      "Yesler, Henry L. (Henry Leiter), 1810-1892",
      "Washington, Lake (Wash.)"
    ],
    "photographer": "Conn, Margaret, 1864-1942",
    "intersection": "",
    "coordinates": [
      47.65,
      -122.276988
    ],
    "createdDate": "1893-01-01T00:00:00.000Z",
    "image": "https://cdm16118.contentdm.oclc.org/digital/api/singleitem/image/p15015coll4/1723/default.jpg"
  },
  {
    "title": "Coxey's Army: Camp Goodwin, 1894",
    "identifier": "spl_shp_14282",
    "description": "Transcribed from photograph: \"Coxey's Army. 1894. Camp Goodwin. Ninth Ave. between Columbia St. and Marion St. Camp of U.S. soldiers brought to Seattle to protect Judge C.H. Hanford and prevent riots during trial of members of Coxey's army.\" Coxey was a business person who led an army of unemployed to Washington, DC in 1894 to plea for a Federal roads program.",
    "subjects": [
      "Buildings--Washington (State)--Seattle",
      "Dwellings--Washington (State)--Seattle",
      "Tents--Washington (State)--Seattle",
      "Ninth Avenue (Seattle, Wash.)",
      "Columbia Street (Seattle, Wash.)",
      "Marion Street (Seattle, Wash.)",
      "Hanford, C. H. (Cornelius Holgate), 1849-1926",
      "Coxey, Jacob Sechler, 1854-1951",
      "Unemployed--Washington (State)--Seattle",
      "Soldiers",
      "Goodwin, W. P."
    ],
    "photographer": "",
    "intersection": "9th Ave. and Columbia St.",
    "coordinates": [
      47.606983,
      -122.32606
    ],
    "createdDate": "1894-01-01T00:00:00.000Z",
    "image": "https://cdm16118.contentdm.oclc.org/digital/api/singleitem/image/p15015coll4/1721/default.jpg"
  },
  {
    "title": "Snowball Fight at Seattle Female College, 1893",
    "identifier": "spl_shp_14281",
    "description": "Transcribed from photograph: \"Schools. Seattle Female College. Ravenna Park. Built 1891; demolished 1893. From the Southeast.\"",
    "subjects": [
      "Ravenna Park (Seattle, Wash.)",
      "Parks--Washington (State)--Seattle",
      "Seattle Female College (Seattle, Wash.)",
      "Private universities and colleges--Washington (State)--Seattle",
      "Women's colleges--Washington (State)--Seattle",
      "Buildings--Washington (State)--Seattle",
      "Snow",
      "Children"
    ],
    "photographer": "Conn, Margaret, 1864-1942",
    "intersection": "",
    "coordinates": [
      47.668856,
      -122.303893
    ],
    "createdDate": "1893-01-01T00:00:00.000Z",
    "image": "https://cdm16118.contentdm.oclc.org/digital/api/singleitem/image/p15015coll4/1720/default.jpg"
  },
  {
    "title": "Sulphur Springs at Ravenna Park, 1893",
    "identifier": "spl_shp_14279",
    "description": "Transcribed from photograph: \"Parks. Ravenna Park. Sulphur Springs. 1893.\"",
    "subjects": [
      "Ravenna Park (Seattle, Wash.)",
      "Parks--Washington (State)--Seattle",
      "Children",
      "Sulfur springs--Washington (State)--Seattle",
      "Baby carriages"
    ],
    "photographer": "Conn, Margaret, 1864-1942",
    "intersection": "",
    "coordinates": [
      47.668856,
      -122.303893
    ],
    "createdDate": "1893-01-01T00:00:00.000Z",
    "image": "https://cdm16118.contentdm.oclc.org/digital/api/singleitem/image/p15015coll4/1718/default.jpg"
  },
  {
    "title": "Train Load of Logs at Yesler (Town), 1893",
    "identifier": "spl_shp_14290",
    "description": "Transcribed from photograph: \"Yesler (town). Train load of logs at Yesler's mill. 1893. Yesler's mill built 1890 at the town of Yesler which is now Laurelhurst.\"",
    "subjects": [
      "Laurelhurst (Seattle, Wash.)",
      "Yesler, Henry L. (Henry Leiter), 1810-1892",
      "Sawmills--Washington (State)--Seattle",
      "Railroads--Washington (State)--Seattle",
      "Log transportation",
      "Logging railroads--Washington (State)--Seattle"
    ],
    "photographer": "",
    "intersection": "",
    "coordinates": [
      47.65,
      -122.276988
    ],
    "createdDate": "1893-01-01T00:00:00.000Z",
    "image": "https://cdm16118.contentdm.oclc.org/digital/api/singleitem/image/p15015coll4/1724/default.jpg"
  },
  {
    "title": "Steamer Bailey Gatzert, ca. 1905",
    "identifier": "spl_shp_14283",
    "description": "Transcribed from photograph: \"Ships. Bailey Gatzert (steamer). Built by John J. Holland, launched Nov. 22, 1890. Sailed between Seattle and Olympia until 1892. On Columbia River 1892-1918. On Puget Sound 1918-1928. In 1928 converted to a floating machine shop.\"",
    "subjects": [
      "Gatzert, Bailey, 1829-1893",
      "Bailey Gatzert (Steamship)",
      "Steamboats",
      "Holland, John J.",
      "Cascade Locks (Or.)",
      "Locks (Hydraulic engineering)--Oregon--Cascade Locks"
    ],
    "photographer": "",
    "intersection": "",
    "coordinates": [
      45.667896,
      -121.896804
    ],
    "createdDate": "1905-01-01T00:00:00.000Z",
    "image": "https://cdm16118.contentdm.oclc.org/digital/api/singleitem/image/p15015coll4/1722/default.jpg"
  },
  {
    "title": "3rd St. Street Car at Ravenna Park, ca. 1895",
    "identifier": "spl_shp_14277",
    "description": "Transcribed from photograph: \"Transportation. Third St. street car to Lake Union and Ravenna Park. About 1895. Near entrance of Ravenna Park.\"",
    "subjects": [
      "Ravenna Park (Seattle, Wash.)",
      "Parks--Washington (State)--Seattle",
      "Third Street (Seattle, Wash.)",
      "Union, Lake (Wash.)",
      "Cable cars (Streetcars)",
      "Street-railroads--Washington (State)--Seattle",
      "Snow"
    ],
    "photographer": "Conn, Margaret, 1864-1942",
    "intersection": "",
    "coordinates": [
      47.668856,
      -122.303893
    ],
    "createdDate": "1895-01-01T08:00:00.000Z",
    "image": "https://cdm16118.contentdm.oclc.org/digital/api/singleitem/image/p15015coll4/1717/default.jpg"
  },
  {
    "title": "Seattle Female College, 1893",
    "identifier": "spl_shp_14280",
    "description": "Transcribed from photograph: \"Schools. Seattle Female College. Ravenna Park. Built 1891; demolished. 1893. From the South.\"",
    "subjects": [
      "Ravenna Park (Seattle, Wash.)",
      "Parks--Washington (State)--Seattle",
      "Seattle Female College (Seattle, Wash.)",
      "Private universities and colleges--Washington (State)--Seattle",
      "Women's colleges--Washington (State)--Seattle",
      "Buildings--Washington (State)--Seattle",
      "Snow"
    ],
    "photographer": "Conn, Margaret, 1864-1942",
    "intersection": "",
    "coordinates": [
      47.668856,
      -122.303893
    ],
    "createdDate": "1893-01-01T00:00:00.000Z",
    "image": "https://cdm16118.contentdm.oclc.org/digital/api/singleitem/image/p15015coll4/1719/default.jpg"
  },
  {
    "title": "Seattle Female College, 1893",
    "identifier": "spl_shp_14276",
    "description": "Transcribed from photograph: \"Schools. Seattle Female College. Ravenna Park. Built 1891; demolished 1893. From the East. Seattle Flouring Mill at right.\"",
    "subjects": [
      "Ravenna Park (Seattle, Wash.)",
      "Parks--Washington (State)--Seattle",
      "Seattle Female College (Seattle, Wash.)",
      "Private universities and colleges--Washington (State)--Seattle",
      "Women's colleges--Washington (State)--Seattle",
      "Seattle Flouring Mill (Seattle, Wash.)",
      "Railroad tracks--Washington (State)--Seattle",
      "Buildings--Washington (State)--Seattle"
    ],
    "photographer": "",
    "intersection": "",
    "coordinates": [
      47.668856,
      -122.303893
    ],
    "createdDate": "1893-01-01T00:00:00.000Z",
    "image": "https://cdm16118.contentdm.oclc.org/digital/api/singleitem/image/p15015coll4/1716/default.jpg"
  },
  {
    "title": "View east from Elliott Bay, 1870",
    "identifier": "spl_shp_14557",
    "description": "Transcribed from photograph: \"Views. From Elliott Bay. 1870. From Harper's News Monthly, Sept. 1870. p. 491.\"",
    "subjects": [
      "Buildings--Washington (State)--Seattle",
      "Waterfronts--Washington (State)--Seattle",
      "Elliott Bay (Wash.)",
      "Harper's new monthly magazine"
    ],
    "photographer": "",
    "intersection": "",
    "coordinates": [
      47.607427,
      -122.370833
    ],
    "createdDate": "1870-01-01T00:00:00.000Z",
    "image": "https://cdm16118.contentdm.oclc.org/digital/api/singleitem/image/p15015coll4/1727/default.jpg"
  },
  {
    "title": "Alaska Yukon Pacific Exposition Forestry Building, 1909",
    "identifier": "spl_shp_14535",
    "description": "Transcribed from photograph: \"Alaska Yukon Pacific Exposition. 1909. Forestry building. Saunders and Lawton, architects.\"",
    "subjects": [
      "Alaska-Yukon-Pacific Exposition (1909 : Seattle, Wash.)",
      "Exhibitions--Washington (State)--Seattle",
      "Exhibition buildings--Washington (State)--Seattle",
      "Forests and forestry--Washington (State)--Seattle",
      "Forestry Building (Alaska-Yukon-Pacific Exposition, 1909, Seattle, Wash.)"
    ],
    "photographer": "Nowell, Frank H., 1864-1950",
    "intersection": "",
    "coordinates": [
      47.655079,
      -122.305959
    ],
    "createdDate": "1909-01-01T00:00:00.000Z",
    "image": "https://cdm16118.contentdm.oclc.org/digital/api/singleitem/image/p15015coll4/1726/default.jpg"
  },
  {
    "title": "Parade for President Wilson, September 12, 1919",
    "identifier": "spl_shp_14574",
    "description": "Transcribed from photograph: \"Pacific Fleet. Review, Sept. 12-14, 1919. Parade for President Wilson. Second Ave. looking South from Stewart St.\"",
    "subjects": [
      "Parades--Washington (State)--Seattle",
      "Wilson, Woodrow, 1856-1924",
      "Central business districts--Washington (State)--Seattle",
      "Office buildings--Washington (State)--Seattle",
      "Buildings--Washington (State)--Seattle",
      "Second Avenue (Seattle, Wash.)",
      "Stewart Street (Seattle, Wash.)",
      "Signs and signboards",
      "James & Merrihew (Seattle, Wash.)",
      "Photographers",
      "Seattle (Wash.)--Population",
      "Crowds"
    ],
    "photographer": "",
    "intersection": "2nd Ave. and Stewart St.",
    "coordinates": [
      47.610703,
      -122.340332
    ],
    "createdDate": "1919-09-12T00:00:00.000Z",
    "image": "https://cdm16118.contentdm.oclc.org/digital/api/singleitem/image/p15015coll4/1738/default.jpg"
  },
  {
    "title": "Destroyer saluting President Wilson, September 12, 1919",
    "identifier": "spl_shp_14575",
    "description": "Transcribed from photograph: \"Pacific Fleet. Review, Sept. 12-14, 1919. Destroyer saluting President Wilson.\"",
    "subjects": [
      "United States. Navy",
      "Warships",
      "Destroyers (Warships)",
      "Wilson, Woodrow, 1856-1924",
      "Elliott Bay (Wash.)",
      "Naval ceremonies, honors, and salutes--Washington (State)--Seattle"
    ],
    "photographer": "",
    "intersection": "",
    "coordinates": [
      47.607427,
      -122.370833
    ],
    "createdDate": "1919-09-12T00:00:00.000Z",
    "image": "https://cdm16118.contentdm.oclc.org/digital/api/singleitem/image/p15015coll4/1739/default.jpg"
  },
  {
    "title": "King County Courthouse  and City Hall park on Third Ave and Jefferson St., 1924",
    "identifier": "spl_shp_14566",
    "description": "Transcribed from photograph: \"Buildings. King County courthouse. Third Ave. and Jefferson St. Built 1915-16. 1924. A. Warren Gould, architect. City Hall park in foreground.\"",
    "subjects": [
      "Buildings--Washington (State)--Seattle",
      "Courthouses--Washington (State)--Seattle",
      "Courthouses--Washington (State)--King County",
      "King County Courthouse (Seattle, Wash.)",
      "Courts--Washington (State)--Seattle",
      "Courts--Washington (State)--King County",
      "Third Avenue (Seattle, Wash.)",
      "Jefferson Street (Seattle, Wash.)",
      "City Hall Park (Seattle, Wash.)",
      "Parks--Washington (State)--Seattle"
    ],
    "photographer": "Webster & Stevens",
    "intersection": "3rd Ave. and Jefferson St.",
    "coordinates": [
      47.602132,
      -122.330816
    ],
    "createdDate": "1924-01-01T00:00:00.000Z",
    "image": "https://cdm16118.contentdm.oclc.org/digital/api/singleitem/image/p15015coll4/1731/default.jpg"
  },
  {
    "title": "Harbor activities during Pacific Fleet Review, September 12, 1919",
    "identifier": "spl_shp_14573",
    "description": "Transcribed from photograph: \"Pacific Fleet. Review, Sept. 12-14, 1919. Harbor activities. Battleship Oregon in background.\"",
    "subjects": [
      "United States. Navy",
      "Warships",
      "Battleships",
      "Oregon (Battleship)",
      "Wilson, Woodrow, 1856-1924",
      "Elliott Bay (Wash.)",
      "Piers--Washington (State)--Seattle",
      "Docks--Washington (State)--Seattle",
      "Wharves--Washington (State)--Seattle",
      "Waterfronts--Washington (State)--Seattle",
      "Sailors",
      "Naval ceremonies, honors, and salutes--Washington (State)--Seattle"
    ],
    "photographer": "",
    "intersection": "",
    "coordinates": [
      47.607427,
      -122.370833
    ],
    "createdDate": "1919-09-12T00:00:00.000Z",
    "image": "https://cdm16118.contentdm.oclc.org/digital/api/singleitem/image/p15015coll4/1737/default.jpg"
  },
  {
    "title": "Quarterdeck of the Battleship \"New Mexico,\" September 12, 1919",
    "identifier": "spl_shp_14569",
    "description": "Transcribed from photograph: \"Pacific Fleet. Review, Sept. 12-14, 1919. Battleship New Mexico. Quarterdeck. Flagship of Admiral Rocman [i.e. Rodman].\"",
    "subjects": [
      "Waterfronts--Washington (State)--Seattle",
      "United States. Navy",
      "Warships",
      "Battleships",
      "Sailors",
      "New Mexico (Battleship)",
      "Rodman, Hugh, 1859-1940",
      "Elliott Bay (Wash.)",
      "Naval ceremonies, honors, and salutes--Washington (State)--Seattle"
    ],
    "photographer": "",
    "intersection": "",
    "coordinates": [
      47.607427,
      -122.370833
    ],
    "createdDate": "1919-09-12T00:00:00.000Z",
    "image": "https://cdm16118.contentdm.oclc.org/digital/api/singleitem/image/p15015coll4/1733/default.jpg"
  },
  {
    "title": "President Wilson arriving in Seattle for Pacific Fleet Review, September 12, 1919",
    "identifier": "spl_shp_14572",
    "description": "Transcribed from photograph: \"Pacific Fleet. Review, Sept. 12-14, 1919. President Wilson arriving in Seattle.\"",
    "subjects": [
      "Railroad stations--Washington (State)--Seattle",
      "King Street Station (Seattle, Wash.)",
      "Buildings--Washington (State)--Seattle",
      "Wilson, Woodrow, 1856-1924",
      "Presidential automobiles",
      "Special weeks--Washington (State)--Seattle"
    ],
    "photographer": "",
    "intersection": "",
    "coordinates": [
      47.599013,
      -122.329933
    ],
    "createdDate": "1919-09-12T00:00:00.000Z",
    "image": "https://cdm16118.contentdm.oclc.org/digital/api/singleitem/image/p15015coll4/1736/default.jpg"
  },
  {
    "title": "President and Mrs. Wilson reviewing fleet from bridge of the Oregon, September 12, 1919",
    "identifier": "spl_shp_14570",
    "description": "Transcribed from photograph: \"Pacific Fleet. Review, Sept. 12-14, 1919. Official party reviewing fleet from bridge of the Oregon. 1. Mrs. Wilson. 2. President Wilson. 3. Secretary of the Navy Daniels. 4. Mrs. Daniels.\"",
    "subjects": [
      "United States. Navy",
      "Warships",
      "Oregon (Battleship)",
      "Wilson, Woodrow, 1856-1924",
      "Wilson, Edith Bolling Galt, 1872-1961",
      "Daniels, Josephus, 1862-1948",
      "Daniels, Addie Worth Bagley, 1869-1943",
      "Naval ceremonies, honors, and salutes--Washington (State)--Seattle"
    ],
    "photographer": "",
    "intersection": "",
    "coordinates": [
      47.607427,
      -122.370833
    ],
    "createdDate": "1919-09-12T00:00:00.000Z",
    "image": "https://cdm16118.contentdm.oclc.org/digital/api/singleitem/image/p15015coll4/1734/default.jpg"
  },
  {
    "title": "John Hay School, ca. 1922",
    "identifier": "spl_shp_14565",
    "description": "Transcribed from photograph: \"Schools. John Hay school. Fourth Ave. North and Newton St. Addition. Built 1922. Floyd A. Naramore, architect.\"",
    "subjects": [
      "Buildings--Washington (State)--Seattle",
      "John Hay Elementary School (Seattle, Wash.)",
      "Elementary schools--Washington (State)--Seattle",
      "Fourth Avenue North (Seattle, Wash.)",
      "Newton Street (Seattle, Wash.)",
      "Children",
      "Stairs"
    ],
    "photographer": "",
    "intersection": "4th Ave. N and Newton St.",
    "coordinates": [
      47.636565,
      -122.349506
    ],
    "createdDate": "1922-01-01T08:00:00.000Z",
    "image": "https://cdm16118.contentdm.oclc.org/digital/api/singleitem/image/p15015coll4/1730/default.jpg"
  },
  {
    "title": "Great Northern Dock, Smith's Cove, ca. 1926",
    "identifier": "spl_shp_14561",
    "description": "Transcribed from photograph: \"Wharves. Great Northern dock, Smith's Cove. Built 1898-1899. About 1926. Steamer Kashima Maru at dock.\"",
    "subjects": [
      "Buildings--Washington (State)--Seattle",
      "Waterfronts--Washington (State)--Seattle",
      "Piers--Washington (State)--Seattle",
      "Docks--Washington (State)--Seattle",
      "Wharves--Washington (State)--Seattle",
      "Railroads--Washington (State)--Seattle",
      "Great Northern Railway Company (U.S.)",
      "Smith Cove (King County, Wash.)",
      "Kashima Maru (Ship)",
      "Steamboats"
    ],
    "photographer": "",
    "intersection": "",
    "coordinates": [
      47.629083,
      -122.381631
    ],
    "createdDate": "1926-01-01T08:00:00.000Z",
    "image": "https://cdm16118.contentdm.oclc.org/digital/api/singleitem/image/p15015coll4/1729/default.jpg"
  },
  {
    "title": "Fraser and Wilson Store on Pike St., ca. 1895",
    "identifier": "spl_shp_14568",
    "description": "Transcribed from photograph: \"Buildings. Fraser and Wilson store. 423 Pike St. 1895?\"",
    "subjects": [
      "Buildings--Washington (State)--Seattle",
      "Storefronts--Washington (State)--Seattle",
      "Central business districts--Washington (State)--Seattle",
      "Pike Street (Seattle, Wash.)",
      "Dry-goods",
      "Stores, Retail--Washington (State)--Seattle",
      "Fraser & Wilson (Seattle, Wash.)",
      "Fraser, John, 1856-1930",
      "Wilson, Alexander, b. 1861?"
    ],
    "photographer": "",
    "intersection": "",
    "coordinates": [
      47.610379,
      -122.336303
    ],
    "createdDate": "1895-01-01T08:00:00.000Z",
    "image": "https://cdm16118.contentdm.oclc.org/digital/api/singleitem/image/p15015coll4/1732/default.jpg"
  },
  {
    "title": "Parade for President Wilson on 2nd Ave., September 12, 1919",
    "identifier": "spl_shp_14571",
    "description": "Transcribed from photograph: \"Pacific Fleet. Review, Sept. 12-14, 1919. Parade for President Wilson. The President's automobile. Second Ave. looking South from Madison St.\"",
    "subjects": [
      "Parades--Washington (State)--Seattle",
      "Wilson, Woodrow, 1856-1924",
      "Presidential automobiles",
      "Central business districts--Washington (State)--Seattle",
      "Office buildings--Washington (State)--Seattle",
      "Buildings--Washington (State)--Seattle",
      "Second Avenue (Seattle, Wash.)",
      "Smith Tower (Seattle, Wash.)",
      "Tall buildings--Washington (State)--Seattle",
      "Special weeks--Washington (State)--Seattle",
      "Clocks and watches",
      "Jewelry stores--Washington (State)--Seattle",
      "Albert Hanson Jewelers (Seattle, Wash.)",
      "Leary Building (Seattle, Wash.)"
    ],
    "photographer": "",
    "intersection": "",
    "coordinates": [
      47.605626,
      -122.335541
    ],
    "createdDate": "1919-09-12T00:00:00.000Z",
    "image": "https://cdm16118.contentdm.oclc.org/digital/api/singleitem/image/p15015coll4/1735/default.jpg"
  },
  {
    "title": "American Can Co. Alaskan Way and Cedar St., ca. 1925",
    "identifier": "spl_shp_14558",
    "description": "Transcribed from photograph: \"Buildings. American Can Co. Alaskan Way and Cedar St. About 1925.\"",
    "subjects": [
      "Buildings--Washington (State)--Seattle",
      "Alaskan Way (Seattle, Wash.)",
      "Cedar Street (Seattle, Wash.)",
      "American Can Company (Seattle, Wash.)",
      "Aluminum cans",
      "Container industry--Washington (State)--Seattle",
      "Railroads--Washington (State)--Seattle",
      "Railroad cars",
      "Skywalks--Washington (State)--Seattle"
    ],
    "photographer": "Curtis, Asahel, 1874-1941",
    "intersection": "Alaskan Way and Cedar St.",
    "coordinates": [
      47.613881,
      -122.35311
    ],
    "createdDate": "1925-01-01T08:00:00.000Z",
    "image": "https://cdm16118.contentdm.oclc.org/digital/api/singleitem/image/p15015coll4/1728/default.jpg"
  },
  {
    "title": "Battleship Mississippi, September 12, 1919",
    "identifier": "spl_shp_14576",
    "description": "Transcribed from photograph: \"Pacific Fleet. Review, Sept. 12-14, 1919. Battleship Mississippi.\"",
    "subjects": [
      "United States. Navy",
      "Warships",
      "Mississippi (Battleship : BB 41)",
      "Wilson, Woodrow, 1856-1924",
      "Elliott Bay (Wash.)",
      "Naval ceremonies, honors, and salutes--Washington (State)--Seattle",
      "Waterfronts--Washington (State)--Seattle",
      "Buildings--Washington (State)--Seattle",
      "Smith Tower (Seattle, Wash.)"
    ],
    "photographer": "",
    "intersection": "",
    "coordinates": [
      47.607427,
      -122.370833
    ],
    "createdDate": "1919-09-12T00:00:00.000Z",
    "image": "https://cdm16118.contentdm.oclc.org/digital/api/singleitem/image/p15015coll4/1740/default.jpg"
  },
  {
    "title": "Fleet coming into Seattle harbor, September 12, 1919",
    "identifier": "spl_shp_14577",
    "description": "Transcribed from photograph: \"Pacific Fleet. Review, Sept. 12-14,1919. Fleet coming into Seattle harbor.\"",
    "subjects": [
      "United States. Navy",
      "Warships",
      "Elliott Bay (Wash.)",
      "Naval ceremonies, honors, and salutes--Washington (State)--Seattle",
      "Sailors"
    ],
    "photographer": "",
    "intersection": "",
    "coordinates": [
      47.607427,
      -122.370833
    ],
    "createdDate": "1919-09-12T00:00:00.000Z",
    "image": "https://cdm16118.contentdm.oclc.org/digital/api/singleitem/image/p15015coll4/1741/default.jpg"
  },
  {
    "title": "Destroyers in review, September 12, 1919",
    "identifier": "spl_shp_14579",
    "description": "Transcribed from photograph: \"Pacific Fleet. Review, Sept. 12-14, 1919. Destroyers in review.\"",
    "subjects": [
      "United States. Navy",
      "Warships",
      "Destroyers (Warships)",
      "Elliott Bay (Wash.)",
      "Naval ceremonies, honors, and salutes--Washington (State)--Seattle"
    ],
    "photographer": "",
    "intersection": "",
    "coordinates": [
      47.607427,
      -122.370833
    ],
    "createdDate": "1919-09-12T00:00:00.000Z",
    "image": "https://cdm16118.contentdm.oclc.org/digital/api/singleitem/image/p15015coll4/1743/default.jpg"
  },
  {
    "title": "Forward deck of Battleship New Mexico, September 12, 1919",
    "identifier": "spl_shp_14585",
    "description": "Transcribed from photograph: \"Pacific Fleet. Review, Sept. 12-14, 1919. Battleship new Mexico. Forward deck showing 14 inch guns. Flagship of Admiral Rodman.\"",
    "subjects": [
      "Waterfronts--Washington (State)--Seattle",
      "United States. Navy",
      "Warships",
      "Sailors",
      "New Mexico (Battleship)",
      "Rodman, Hugh, 1859-1940",
      "Elliott Bay (Wash.)",
      "Naval ceremonies, honors, and salutes--Washington (State)--Seattle"
    ],
    "photographer": "",
    "intersection": "",
    "coordinates": [
      47.607427,
      -122.370833
    ],
    "createdDate": "1919-09-12T00:00:00.000Z",
    "image": "https://cdm16118.contentdm.oclc.org/digital/api/singleitem/image/p15015coll4/1749/default.jpg"
  },
  {
    "title": "Battleship Texas, September 12, 1919",
    "identifier": "spl_shp_14582",
    "description": "Transcribed from photograph: \"Pacific Fleet. Review, Sept. 12-14, 1919. Battleship Texas.\"",
    "subjects": [
      "United States. Navy",
      "Warships",
      "Destroyers (Warships)",
      "Elliott Bay (Wash.)",
      "Naval ceremonies, honors, and salutes--Washington (State)--Seattle"
    ],
    "photographer": "",
    "intersection": "",
    "coordinates": [
      47.607427,
      -122.370833
    ],
    "createdDate": "1919-09-12T00:00:00.000Z",
    "image": "https://cdm16118.contentdm.oclc.org/digital/api/singleitem/image/p15015coll4/1745/default.jpg"
  },
  {
    "title": "Fleet rounding Magnolia Bluff, September 12, 1919",
    "identifier": "spl_shp_14578",
    "description": "Transcribed from photograph: \"Pacific Fleet. Review, Sept. 12-14, 1919. Fleet rounding Magnolia Bluff. Battleships: 1. New York. 2. Texas. 3. Wyoming. 4. Idaho. 5. Mississippi.\"",
    "subjects": [
      "United States. Navy",
      "Warships",
      "Battleships",
      "Naval ceremonies, honors, and salutes--Washington (State)--Seattle",
      "Magnolia (Seattle, Wash.)",
      "New York (Battleship : BB-34)",
      "Texas (Battleship)",
      "Wyoming (Battleship)",
      "Idaho (Battleship : BB-42)",
      "Mississippi (Battleship : BB 41)"
    ],
    "photographer": "",
    "intersection": "",
    "coordinates": [
      47.607427,
      -122.370833
    ],
    "createdDate": "1919-09-12T00:00:00.000Z",
    "image": "https://cdm16118.contentdm.oclc.org/digital/api/singleitem/image/p15015coll4/1742/default.jpg"
  },
  {
    "title": "Battleship New York, September 12, 1919",
    "identifier": "spl_shp_14586",
    "description": "Transcribed from photograph: \"Pacific Fleet. Review, Sept. 12-14, 1919. Battleship New York.\"",
    "subjects": [
      "United States. Navy",
      "Warships",
      "Battleships",
      "Elliott Bay (Wash.)",
      "Naval ceremonies, honors, and salutes--Washington (State)--Seattle",
      "Waterfronts--Washington (State)--Seattle",
      "New York (Battleship : BB-34)",
      "Buildings--Washington (State)--Seattle"
    ],
    "photographer": "",
    "intersection": "",
    "coordinates": [
      47.607427,
      -122.370833
    ],
    "createdDate": "1919-09-12T00:00:00.000Z",
    "image": "https://cdm16118.contentdm.oclc.org/digital/api/singleitem/image/p15015coll4/1750/default.jpg"
  },
  {
    "title": "Battleships in Harbor, September 12, 1919",
    "identifier": "spl_shp_14580",
    "description": "Transcribed from photograph: \"Pacific Fleet. Review, Sept. 12-14, 1919. Battleships in harbor. 1. Texas. 2. Idaho. 3. Mississippi.\"",
    "subjects": [
      "United States. Navy",
      "Warships",
      "Battleships",
      "Elliott Bay (Wash.)",
      "Naval ceremonies, honors, and salutes--Washington (State)--Seattle",
      "Texas (Battleship)",
      "Idaho (Battleship : BB-42)",
      "Mississippi (Battleship : BB 41)",
      "Waterfronts--Washington (State)--Seattle",
      "Buildings--Washington (State)--Seattle"
    ],
    "photographer": "",
    "intersection": "",
    "coordinates": [
      47.607427,
      -122.370833
    ],
    "createdDate": "1919-09-12T00:00:00.000Z",
    "image": "https://cdm16118.contentdm.oclc.org/digital/api/singleitem/image/p15015coll4/1744/default.jpg"
  },
  {
    "title": "Destroyer, September 12, 1919",
    "identifier": "spl_shp_14581",
    "description": "Transcribed from photograph: \"Pacific Fleet. Review, Sept. 12-14, 1919. Destroyer.\"",
    "subjects": [
      "United States. Navy",
      "Warships",
      "Battleships",
      "Elliott Bay (Wash.)",
      "Naval ceremonies, honors, and salutes--Washington (State)--Seattle",
      "Texas (Battleship)",
      "Sailors",
      "Magnolia (Seattle, Wash.)",
      "Flags--United States"
    ],
    "photographer": "",
    "intersection": "",
    "coordinates": [
      47.607427,
      -122.370833
    ],
    "createdDate": "1919-09-12T00:00:00.000Z",
    "image": "https://cdm16118.contentdm.oclc.org/digital/api/singleitem/image/p15015coll4/1746/default.jpg"
  },
  {
    "title": "Destroyers in harbor, September 12, 1919",
    "identifier": "spl_shp_14584",
    "description": "Transcribed from photograph: \"Pacific Fleet. Review, Sept. 12-14, 1919. Destroyers in harbor.\"",
    "subjects": [
      "United States. Navy",
      "Warships",
      "Destroyers (Warships)",
      "Elliott Bay (Wash.)",
      "Naval ceremonies, honors, and salutes--Washington (State)--Seattle"
    ],
    "photographer": "",
    "intersection": "",
    "coordinates": [
      47.607427,
      -122.370833
    ],
    "createdDate": "1919-09-12T00:00:00.000Z",
    "image": "https://cdm16118.contentdm.oclc.org/digital/api/singleitem/image/p15015coll4/1748/default.jpg"
  },
  {
    "title": "Battleship New Mexico, September 12, 1919",
    "identifier": "spl_shp_14587",
    "description": "Transcribed from photograph: \"Pacific Fleet. Review, Sept. 12-14, 1919. Battleship New Mexico. Flagship of Admiral Rodman.\"",
    "subjects": [
      "Waterfronts--Washington (State)--Seattle",
      "United States. Navy",
      "Warships",
      "Battleships",
      "New Mexico (Battleship)",
      "Rodman, Hugh, 1859-1940",
      "Elliott Bay (Wash.)",
      "Naval ceremonies, honors, and salutes--Washington (State)--Seattle",
      "Buildings--Washington (State)--Seattle",
      "Central business districts--Washington (State)--Seattle",
      "Smith Tower (Seattle, Wash.)"
    ],
    "photographer": "",
    "intersection": "",
    "coordinates": [
      47.607427,
      -122.370833
    ],
    "createdDate": "1919-09-12T00:00:00.000Z",
    "image": "https://cdm16118.contentdm.oclc.org/digital/api/singleitem/image/p15015coll4/1751/default.jpg"
  },
  {
    "title": "Destroyers in review, September 12, 1919",
    "identifier": "spl_shp_14583",
    "description": "Transcribed from photograph: \"Pacific Fleet. Review, Sept. 12-14, 1919. Destroyers in review.\"",
    "subjects": [
      "United States. Navy",
      "WarShips",
      "Destroyers (Warships)",
      "Elliott Bay (Wash.)",
      "Naval ceremonies, honors, and salutes--Washington (State)--Seattle",
      "Magnolia (Seattle, Wash.)"
    ],
    "photographer": "",
    "intersection": "",
    "coordinates": [
      47.607427,
      -122.370833
    ],
    "createdDate": "1919-09-12T00:00:00.000Z",
    "image": "https://cdm16118.contentdm.oclc.org/digital/api/singleitem/image/p15015coll4/1747/default.jpg"
  },
  {
    "title": "Wharves at foot of S. Main St., June 6, 1889",
    "identifier": "spl_shp_14604",
    "description": "Transcribed from photograph: \"Fire. June 6, 1889. Ruins. Wharves at foot of Main St.\"",
    "subjects": [
      "Buildings--Washington (State)--Seattle",
      "Wharves--Washington (State)--Seattle",
      "Waterfronts--Washington (State)--Seattle",
      "South Main Street (Seattle, Wash.)",
      "Elliott Bay (Wash.)",
      "West Seattle (Seattle, Wash.)",
      "Fires--Washington (State)--Seattle",
      "Great Fire, Seattle, Wash., 1889"
    ],
    "photographer": "Soule, John P.",
    "intersection": "Alaskan Way S. and S. Main St.",
    "coordinates": [
      47.600037,
      -122.335947
    ],
    "createdDate": "1889-06-06T00:00:00.000Z",
    "image": "https://cdm16118.contentdm.oclc.org/digital/api/singleitem/image/p15015coll4/1757/default.jpg"
  }
]